{
  "last_updated": "2025-07-03T12:41:22.407538+00:00",
  "videos": [
    "xGEVdmqPfug",
    "bx_cyZ1wYVw",
    "XaONuG_ifKs",
    "G4WzSiFTyZY",
    "5nrvU5k4Gso",
    "3YaJUloWUrg",
    "tQDPzjXrrP8",
    "VrXCusfFY4s",
    "1B9i267_ps4",
    "1PSAPcU8dwI",
    "c7jigN39dWw",
    "Xb2N4CWdelc",
    "IhAD1Yg1fS4",
    "yTEIquUolBI",
    "g1ckl_FP6z8",
    "UiHwN04ue-c",
    "jAuA3ZX1NGo",
    "f9G37Kgp3KQ",
    "MpaQXPTqIZ8",
    "BmoqiFRe_Xk",
    "dBKy__yfims",
    "XGBtxZuhfSQ",
    "TsE5nVH-IgE",
    "BnwX0GAcvkE",
    "W4oDURUZOvI",
    "vklnEnMdTlA",
    "3eQ7kwXuykk",
    "876U0wEMyRo",
    "BeyCm0sZfOM",
    "trGUE08Sujs"
  ],
  "durations": [
    43,
    36,
    65,
    43,
    34,
    1530,
    2035,
    995,
    1780,
    796,
    903,
    542,
    496,
    80,
    76,
    64,
    1140,
    63,
    72,
    58,
    32,
    49,
    56,
    53,
    1836,
    53,
    984,
    21,
    28,
    1243
  ],
  "total_duration": 15206,
  "current_position": 12960
}