{
  "last_updated": "2025-07-04T04:30:19.841933+00:00",
  "videos": [
    "NQiZpiG0ymY",
    "obp-sKl4t4U",
    "WvwcYYY3fPI",
    "L74ht4xadnI",
    "Uk8wcmCu_ds",
    "b1YMJEjyEw0",
    "CTnZXj58Tio",
    "QBW4COeChr4",
    "YccxZu6xEoI",
    "m-Q9d4lq2kM",
    "IDzvBUdfnTg",
    "VwWnrL7c9x8",
    "-Xbiap25ZyA",
    "6WfVukg0Y2I",
    "aIdXlNtCNAI",
    "4LGXItSF5uU",
    "zTAza3ZxD20",
    "G2OI_gpD3x0",
    "o1Gw72171Pc",
    "_FFzNBsJ8-U",
    "bLmThiHHDuY",
    "WohYBiNfouA",
    "yBZ44Ou7u_8",
    "x51s6rMoXNs",
    "SN5zevnSRNg",
    "yyzsxSiR0V0",
    "TeDJA_cLqVE",
    "4g9uO8GlV3Y",
    "V11uBi1v-tU",
    "q0w7IBU77KE"
  ],
  "durations": [
    1068,
    38,
    1040,
    1156,
    71,
    76,
    48,
    82,
    29,
    53,
    74,
    81,
    892,
    29,
    33,
    51,
    78,
    87,
    31,
    30,
    224,
    1211,
    51,
    35,
    67,
    49,
    29,
    60,
    1033,
    574
  ],
  "total_duration": 8380,
  "current_position": 7439
}